odoo/addons/pos_partner_second_lastname/README.rst
odoo/addons/pos_partner_second_lastname/__init__.py
odoo/addons/pos_partner_second_lastname/__manifest__.py
odoo/addons/pos_partner_second_lastname/i18n/es.po
odoo/addons/pos_partner_second_lastname/i18n/fr.po
odoo/addons/pos_partner_second_lastname/i18n/it.po
odoo/addons/pos_partner_second_lastname/i18n/pos_partner_second_lastname.pot
odoo/addons/pos_partner_second_lastname/models/__init__.py
odoo/addons/pos_partner_second_lastname/models/pos_session.py
odoo/addons/pos_partner_second_lastname/readme/CONTRIBUTORS.md
odoo/addons/pos_partner_second_lastname/readme/DESCRIPTION.md
odoo/addons/pos_partner_second_lastname/static/description/icon.png
odoo/addons/pos_partner_second_lastname/static/description/index.html
odoo/addons/pos_partner_second_lastname/static/src/app/PartnerDetailsEdit.esm.js
odoo/addons/pos_partner_second_lastname/static/src/app/PartnerDetailsEdit.xml
odoo_addon_pos_partner_second_lastname-17.0.1.0.0.8.dist-info/METADATA
odoo_addon_pos_partner_second_lastname-17.0.1.0.0.8.dist-info/WHEEL
odoo_addon_pos_partner_second_lastname-17.0.1.0.0.8.dist-info/top_level.txt
odoo_addon_pos_partner_second_lastname-17.0.1.0.0.8.dist-info/RECORD
